deckbro/__init__.py
deckbro/deck.py
deckbro/render.py
deckbro/svg.py
deckbro/text_rect_template.html
deckbro/tests/__init__.py
deckbro/tests/test_create_text_fitting_rect.py
deckbro/tests/test_find_first_of.py
deckbro/tests/test_inverleave_front_back.py
deckbro/tests/test_reorder_backs.py
deckbro/tests/test_replace_all.py
deckbro/tests/test_svg_strip_svg_tag.py
deckbro-0.0.1.dist-info/licenses/LICENSE
deckbro-0.0.1.dist-info/METADATA
deckbro-0.0.1.dist-info/WHEEL
deckbro-0.0.1.dist-info/top_level.txt
deckbro-0.0.1.dist-info/RECORD
