Metadata-Version: 2.4
Name: deckbro
Version: 0.0.1
Summary: Generate playing cards deck from python config and SVG templates.
Author-email: Félix Bertoni <felix.bertoni987@gmail.com>
License-Expression: CECILL-2.1
Project-URL: Homepage, https://gitlab.com/feloxyde/deckbro
Keywords: deck,card,svg
Classifier: Programming Language :: Python :: 3
Classifier: Operating System :: OS Independent
Classifier: Development Status :: 3 - Alpha
Requires-Python: >=3.12
License-File: LICENSE
Dynamic: license-file
